pnadcontinua/__init__.py
pnadcontinua/__main__.py
pnadcontinua/constants.py
pnadcontinua/core.py
pnadcontinua/downloaded.json
pnadcontinua/metadata.py
pnadcontinua/utils.py
pnadcontinua/gui/__init__.py
pnadcontinua/gui/app.py
pnadcontinua/gui/frames.py
pnadcontinua-0.0.6.dist-info/LICENSE
pnadcontinua-0.0.6.dist-info/METADATA
pnadcontinua-0.0.6.dist-info/WHEEL
pnadcontinua-0.0.6.dist-info/top_level.txt
pnadcontinua-0.0.6.dist-info/RECORD
